[1,["f6A1GgpdtNL4vICNw200w3","bdv6o6PkZD367VD0XastwD","29gS0Ls8VDS7McYMv1AtfP","abx+YZA45GAK3YH4dJBkMZ","dfr+YgG7dA+58uhjPpX7tS","56Ot/LCXhEOaWqaOwh8xTW","969EMM8QFDeJ18wLAFW0Hb","ccgpJTiW9N75FTFgNyEpdQ","d6xswYNn1NYrcIMw81QGJS","ac0Z25i6JGPocWFcBLZD0W","edDp77JxdLxpHGpqpnJmhD","cceya/RNFBS4Ch6FU/cdof","ebe9yXnjpO3pMTjV3BqDXl","b6VyNBfo1C4Yk4q4trnoca","56GbfK1rNCeo9EC2Fyi09a","2f8g5raGpECZgoU18eUfjE","20I0vc+LdCZ5X7HuRjWNpw","97gyZtX9tOWYl2NzJ541nd","233CLiytVBdao97Gsbp4lV","bcb7UfohNGW7nRyfiipVg7","54tmOmbGVPJq5ubaZ/8lcl","50b9Y6lwVCmrIc32gDnRKR","c1d4B21+tCvrJ7dfCDwn7n","1ap3aCmdRBRbPlTLMZ2SzM","ccgy2oKktGApBiIvFNv7TY","dctE6qWt9Eq43LoPtbgGNz","2eESNijXNPa7g/U5ffDUW0","83ZE/H/tZOWKu7GzitlysO","d3D38IwAdMab6BLtpsBfxb","52E86JvGJMS5D3G1IMg0oh"],["value"],[["cc.AnimationClip",["_name","_duration","sample","wrapMode","curveData"],-1,11]],[[0,0,1,2,3,4,5]],[[0,"Swim",1,30,2,[{},"paths",11,[{},"Shape",11,[{},"comps",11,[{},"cc.Sprite",11,[{},"spriteFrame",12,[[[{"frame":0},"value",6,0],[{"frame":0.03333333333333333},"value",6,1],[{"frame":0.06666666666666667},"value",6,2],[{"frame":0.1},"value",6,3],[{"frame":0.13333333333333333},"value",6,4],[{"frame":0.16666666666666666},"value",6,5],[{"frame":0.2},"value",6,6],[{"frame":0.23333333333333334},"value",6,7],[{"frame":0.26666666666666666},"value",6,8],[{"frame":0.3},"value",6,9],[{"frame":0.3333333333333333},"value",6,10],[{"frame":0.36666666666666664},"value",6,11],[{"frame":0.4},"value",6,12],[{"frame":0.43333333333333335},"value",6,13],[{"frame":0.4666666666666667},"value",6,14],[{"frame":0.5},"value",6,15],[{"frame":0.5333333333333333},"value",6,16],[{"frame":0.5666666666666667},"value",6,17],[{"frame":0.6},"value",6,18],[{"frame":0.6333333333333333},"value",6,19],[{"frame":0.6666666666666666},"value",6,20],[{"frame":0.7},"value",6,21],[{"frame":0.7333333333333333},"value",6,22],[{"frame":0.7666666666666667},"value",6,23],[{"frame":0.8},"value",6,24],[{"frame":0.8333333333333334},"value",6,25],[{"frame":0.8666666666666667},"value",6,26],[{"frame":0.9},"value",6,27],[{"frame":0.9333333333333333},"value",6,28],[{"frame":0.9666666666666667},"value",6,29]],11,11,11,11,11,11,11,11,11,11,11,11,11,11,11,11,11,11,11,11,11,11,11,11,11,11,11,11,11,11]]]]]]]],0,0,[0,0,0,0,0,0,0,0,0,0,0,0,0,0,0,0,0,0,0,0,0,0,0,0,0,0,0,0,0,0],[0,0,0,0,0,0,0,0,0,0,0,0,0,0,0,0,0,0,0,0,0,0,0,0,0,0,0,0,0,0],[0,1,2,3,4,5,6,7,8,9,10,11,12,13,14,15,16,17,18,19,20,21,22,23,24,25,26,27,28,29]]