[1,["b4jSBVzWNMHrQ6T/P1p8by"],["_textureSetter"],["cc.SpriteFrame"],0,[[[{"name":"BOOM_FIRE_025","rect":[1511,1860,146,82],"offset":[0,0],"originalSize":[146,82],"rotated":1,"capInsets":[0,0,0,0]}],[0],0,[0],[0],[0]],[[{"name":"BOOM_FIRE_004","rect":[745,928,68,62],"offset":[39,-10],"originalSize":[146,82],"rotated":1,"capInsets":[0,0,0,0]}],[0],0,[0],[0],[0]],[[{"name":"BOOM_FIRE_001","rect":[743,1068,64,62],"offset":[41,-10],"originalSize":[146,82],"capInsets":[0,0,0,0]}],[0],0,[0],[0],[0]],[[{"name":"BOOM_FIRE_039","rect":[656,1782,116,82],"offset":[15,0],"originalSize":[146,82],"rotated":1,"capInsets":[0,0,0,0]}],[0],0,[0],[0],[0]],[[{"name":"BOOM_FIRE_040","rect":[522,1950,114,82],"offset":[16,0],"originalSize":[146,82],"capInsets":[0,0,0,0]}],[0],0,[0],[0],[0]],[[{"name":"BOOM_FIRE_006","rect":[745,998,68,62],"offset":[39,-10],"originalSize":[146,82],"rotated":1,"capInsets":[0,0,0,0]}],[0],0,[0],[0],[0]],[[{"name":"BOOM_FIRE_000","rect":[1303,359,22,28],"offset":[62,-27],"originalSize":[146,82],"rotated":1,"capInsets":[0,0,0,0]}],[0],0,[0],[0],[0]],[[{"name":"BOOM_FIRE_027","rect":[1629,1797,146,82],"offset":[0,0],"originalSize":[146,82],"capInsets":[0,0,0,0]}],[0],0,[0],[0],[0]],[[{"name":"BOOM_FIRE_028","rect":[1595,1881,146,82],"offset":[0,0],"originalSize":[146,82],"rotated":1,"capInsets":[0,0,0,0]}],[0],0,[0],[0],[0]],[[{"name":"BOOM_FIRE_019","rect":[1706,583,146,82],"offset":[0,0],"originalSize":[146,82],"rotated":1,"capInsets":[0,0,0,0]}],[0],0,[0],[0],[0]],[[{"name":"BOOM_FIRE_010","rect":[340,1121,58,58],"offset":[44,-12],"originalSize":[146,82],"capInsets":[0,0,0,0]}],[0],0,[0],[0],[0]],[[{"name":"BOOM_FIRE_035","rect":[1651,731,136,82],"offset":[5,0],"originalSize":[146,82],"capInsets":[0,0,0,0]}],[0],0,[0],[0],[0]],[[{"name":"BOOM_FIRE_017","rect":[1080,1197,130,82],"offset":[8,0],"originalSize":[146,82],"capInsets":[0,0,0,0]}],[0],0,[0],[0],[0]],[[{"name":"BOOM_FIRE_011","rect":[1248,517,56,50],"offset":[45,-16],"originalSize":[146,82],"rotated":1,"capInsets":[0,0,0,0]}],[0],0,[0],[0],[0]],[[{"name":"BOOM_FIRE_005","rect":[340,989,68,62],"offset":[39,-10],"originalSize":[146,82],"rotated":1,"capInsets":[0,0,0,0]}],[0],0,[0],[0],[0]],[[{"name":"BOOM_FIRE_041","rect":[422,1290,110,70],"offset":[18,-6],"originalSize":[146,82],"capInsets":[0,0,0,0]}],[0],0,[0],[0],[0]],[[{"name":"BOOM_FIRE_031","rect":[1763,1881,146,82],"offset":[0,0],"originalSize":[146,82],"rotated":1,"capInsets":[0,0,0,0]}],[0],0,[0],[0],[0]],[[{"name":"BOOM_FIRE_023","rect":[1343,1860,146,82],"offset":[0,0],"originalSize":[146,82],"rotated":1,"capInsets":[0,0,0,0]}],[0],0,[0],[0],[0]],[[{"name":"BOOM_FIRE_038","rect":[1080,1281,130,82],"offset":[7,0],"originalSize":[146,82],"capInsets":[0,0,0,0]}],[0],0,[0],[0],[0]],[[{"name":"BOOM_FIRE_016","rect":[522,1866,114,82],"offset":[16,0],"originalSize":[146,82],"capInsets":[0,0,0,0]}],[0],0,[0],[0],[0]],[[{"name":"BOOM_FIRE_020","rect":[228,1539,146,82],"offset":[0,0],"originalSize":[146,82],"rotated":1,"capInsets":[0,0,0,0]}],[0],0,[0],[0],[0]],[[{"name":"BOOM_FIRE_037","rect":[522,1782,132,82],"offset":[4,0],"originalSize":[146,82],"capInsets":[0,0,0,0]}],[0],0,[0],[0],[0]],[[{"name":"BOOM_FIRE_009","rect":[340,1059,60,60],"offset":[43,-11],"originalSize":[146,82],"capInsets":[0,0,0,0]}],[0],0,[0],[0],[0]],[[{"name":"BOOM_FIRE_034","rect":[1847,1860,132,82],"offset":[7,0],"originalSize":[146,82],"rotated":1,"capInsets":[0,0,0,0]}],[0],0,[0],[0],[0]],[[{"name":"BOOM_FIRE_013","rect":[1931,1860,102,82],"offset":[22,0],"originalSize":[146,82],"capInsets":[0,0,0,0]}],[0],0,[0],[0],[0]],[[{"name":"BOOM_FIRE_030","rect":[1679,1881,146,82],"offset":[0,0],"originalSize":[146,82],"rotated":1,"capInsets":[0,0,0,0]}],[0],0,[0],[0],[0]],[[{"name":"BOOM_FIRE_022","rect":[338,1206,146,82],"offset":[0,0],"originalSize":[146,82],"rotated":1,"capInsets":[0,0,0,0]}],[0],0,[0],[0],[0]],[[{"name":"BOOM_FIRE_003","rect":[745,858,68,62],"offset":[39,-10],"originalSize":[146,82],"rotated":1,"capInsets":[0,0,0,0]}],[0],0,[0],[0],[0]],[[{"name":"BOOM_FIRE_008","rect":[1148,1129,66,62],"offset":[40,-10],"originalSize":[146,82],"rotated":1,"capInsets":[0,0,0,0]}],[0],0,[0],[0],[0]],[[{"name":"BOOM_FIRE_024","rect":[1427,1860,146,82],"offset":[0,0],"originalSize":[146,82],"rotated":1,"capInsets":[0,0,0,0]}],[0],0,[0],[0],[0]],[[{"name":"BOOM_FIRE_007","rect":[1148,991,68,62],"offset":[39,-10],"originalSize":[146,82],"rotated":1,"capInsets":[0,0,0,0]}],[0],0,[0],[0],[0]],[[{"name":"BOOM_FIRE_026","rect":[1629,1713,146,82],"offset":[0,0],"originalSize":[146,82],"capInsets":[0,0,0,0]}],[0],0,[0],[0],[0]],[[{"name":"BOOM_FIRE_014","rect":[1102,1692,112,82],"offset":[17,0],"originalSize":[146,82],"capInsets":[0,0,0,0]}],[0],0,[0],[0],[0]],[[{"name":"BOOM_FIRE_033","rect":[422,1206,132,82],"offset":[7,0],"originalSize":[146,82],"capInsets":[0,0,0,0]}],[0],0,[0],[0],[0]],[[{"name":"BOOM_FIRE_029","rect":[1545,1713,144,82],"offset":[-1,0],"originalSize":[146,82],"rotated":1,"capInsets":[0,0,0,0]}],[0],0,[0],[0],[0]],[[{"name":"BOOM_FIRE_015","rect":[1102,1776,112,82],"offset":[17,0],"originalSize":[146,82],"capInsets":[0,0,0,0]}],[0],0,[0],[0],[0]],[[{"name":"BOOM_FIRE_032","rect":[1651,899,132,82],"offset":[7,0],"originalSize":[146,82],"capInsets":[0,0,0,0]}],[0],0,[0],[0],[0]],[[{"name":"BOOM_FIRE_036","rect":[1651,815,136,82],"offset":[5,0],"originalSize":[146,82],"capInsets":[0,0,0,0]}],[0],0,[0],[0],[0]],[[{"name":"BOOM_FIRE_002","rect":[1148,1061,66,62],"offset":[40,-10],"originalSize":[146,82],"rotated":1,"capInsets":[0,0,0,0]}],[0],0,[0],[0],[0]],[[{"name":"BOOM_FIRE_021","rect":[1080,1365,146,82],"offset":[0,0],"originalSize":[146,82],"rotated":1,"capInsets":[0,0,0,0]}],[0],0,[0],[0],[0]],[[{"name":"BOOM_FIRE_012","rect":[1551,907,98,82],"offset":[24,0],"originalSize":[146,82],"capInsets":[0,0,0,0]}],[0],0,[0],[0],[0]],[[{"name":"BOOM_FIRE_018","rect":[1706,435,146,82],"offset":[0,0],"originalSize":[146,82],"rotated":1,"capInsets":[0,0,0,0]}],[0],0,[0],[0],[0]]]]