[1,["ecpdLyjvZBwrvm+cedCcQy","1e6167cac","acTUbLAspOFpbl5L7JY/x9","6dpYMoc6pCmLqhi1ZqW0V5","c3f/qc2SpLqau1HCXuo288","e9qPN6dtpGWrPJ/lceAJAI"],["node","label","_spriteFrame","_textureSetter","object","sprite","_N$file","root","_N$target","data"],[["cc.Node",["_name","_prefab","_contentSize","_trs","_components","_parent","_children","_color"],2,4,5,7,9,1,2,5],["Unit",["type","settingV","settingH","sprite","object","label"],2,4,4,1,1,1],["UnitSetting",["size","position","scale"],3,5,5,5],["cc.Sprite",["_sizeMode","_type","node","_materials","_spriteFrame"],1,1,3,6],["cc.Label",["_string","_fontSize","_N$horizontalAlign","_N$verticalAlign","_N$overflow","_isSystemFontUsed","_lineHeight","node","_materials"],-4,1,3],"cc.SpriteFrame",["cc.Node",["_name","_parent","_components","_prefab","_contentSize","_trs","_color"],2,1,12,4,5,7,5],["cc.Node",["_name","_parent","_components","_prefab","_contentSize","_trs"],2,1,2,4,5,7],["cc.PrefabInfo",["fileId","root"],2,1],["cc.Prefab",["_name"],2],["5708fN+SzlIY7cK6pWIqd1K",["node","sizeH","sizeV","background","divide1","icon","description","time","info","button"],3,1,5,5,4,4,4,4,4,4,4],["cc.Button",["_N$transition","node","_N$normalColor","_N$pressedColor","_N$disabledColor","_N$target"],2,1,5,5,5,1],["cc.LabelOutline",["node","_color"],3,1,5]],[[8,0,1,2],[2,1,0,1],[2,1,2,0,1],[1,5,1,2,1],[12,0,1,1],[6,0,1,2,3,4,5,2],[1,0,3,1,2,2],[1,0,4,1,2,2],[2,0,1],[9,0,2],[0,0,6,4,1,2,3,2],[0,0,5,4,1,7,2,3,2],[0,0,5,1,2,3,2],[6,0,1,2,3,6,4,5,2],[7,0,1,2,3,4,2],[7,0,1,2,3,4,5,2],[10,0,1,2,3,4,5,6,7,8,9,1],[8,1,1],[3,0,2,3,4,2],[3,1,0,2,3,3],[3,2,3,1],[11,0,1,2,3,4,5,2],[4,0,1,6,5,2,3,4,7,8,8],[4,0,1,5,2,3,4,7,8,7],[4,0,1,2,3,4,7,8,6]],[[[{"name":"history","rect":[560,985,34,83],"offset":[0,0],"originalSize":[34,83],"rotated":1,"capInsets":[18,18,16,18]}],[5],0,[0],[3],[1]],[[[9,"Object"],[10,"Object",[-10,-11,-12,-13,-14,-15,-16],[[16,-9,[5,755,90],[5,600,90],[6,1,-8,[8,[5,600,90]],[8,[5,755,90]]],[6,1,-7,[1,[1,-140,0,0],[5,12,79]],[1,[1,-200,0,0],[5,12,79]]],[7,2,-6,[2,[1,-90,0,0],[0,0.5,0.5],[5,140,140]],[2,[1,-145,0,0],[0,0.6,0.6],[5,140,140]]],[3,-5,[2,[1,100,0,0],[0,0.7,0.7],[5,400,80]],[2,[1,100,0,0],[0,0.8,0.8],[5,400,80]]],[3,-4,[1,[1,-220,0,0],[5,150,65]],[1,[1,-290.234,0,0],[5,170,80]]],[3,-3,[2,[1,100,-15,0],[0,0.775,0.75],[5,400,50.4]],[2,[1,95,-20,0],[0,0.8,0.8],[5,400,50.4]]],[7,2,-2,[1,[1,271,0,0],[5,50,50]],[1,[1,340,-3,0],[5,74,75]]]]],[17,-1],[5,755,90],[0,-52,0,0,0,0,1,1,1,1]],[11,"button",1,[[18,0,-17,[2],3],[21,1,-19,[4,4293322470],[4,4291348680],[4,3363338360],-18]],[0,"c5DOId1JdGKognChyrN/b6",1],[4,4293322470],[5,74,75],[340,-3,0,0,0,0,1,1,1,1]],[5,"time",1,[[-20,[4,-21,[4,4278190080]]],1,4],[0,"b9QOrL5odBWIF1RfyADLv3",1],[5,170,80],[-290.234,0,0,0,0,0,1,1,1,1]],[5,"description",1,[[-22,[4,-23,[4,4278190080]]],1,4],[0,"8a68FKr+NKBazNcBf/FvEo",1],[5,400,80],[100,0,0,0,0,0,1,0.8,0.8,1]],[13,"info",1,[[-24,[4,-25,[4,4278190080]]],1,4],[0,"aa6/WWt/dI9rU2nnAQmAa7",1],[4,4286113791],[5,400,50.4],[95,-20,0,0,0,0,1,0.8,0.8,1]],[14,"bg",1,[-26],[0,"67z4ExJOVIQ5Ei+3j6g8F0",1],[5,755,90]],[19,1,0,6,[0]],[15,"div",1,[-27],[0,"34Kpj54e9BGqSVtPhQOlC4",1],[5,12,79],[-200,0,0,0,0,0,1,1,1,1]],[20,8,[1]],[12,"icon",1,[0,"5fEdKD1xJBcatYLnH2L7Cs",1],[5,140,140],[-145,0,0,0,0,0,1,0.6,0.6,1]],[22,"07/27/2023\n18:00 PM",24,30,false,1,1,2,3,[4]],[23,"Amazon Gift Card $100\n",35,false,1,1,2,4,[5]],[24,"ABCD-EF12-3456",30,1,1,2,5,[6]]],0,[0,7,1,0,4,2,0,1,13,0,1,11,0,1,12,0,4,10,0,5,9,0,5,7,0,0,1,0,-1,6,0,-2,8,0,-3,2,0,-4,10,0,-5,3,0,-6,4,0,-7,5,0,0,2,0,8,2,0,0,2,0,-1,11,0,0,3,0,-1,12,0,0,4,0,-1,13,0,0,5,0,-1,7,0,-1,9,0,9,1,27],[0,0,0,0,0,0,0,7,9,11,12],[-1,-1,-1,2,-1,-1,-1,2,2,6,6],[0,0,0,3,0,0,0,4,5,2,2]],[[{"name":"divide","rect":[799,291,12,79],"offset":[0,0],"originalSize":[12,79],"capInsets":[0,0,0,0]}],[5],0,[0],[3],[1]]]]