[1,["08w0gx9a9BhZRSYEjpacsr"],["_textureSetter"],["cc.SpriteFrame"],0,[[[{"name":"Shark_dead_0117","rect":[859,1,139,268],"offset":[-7,1],"originalSize":[157,272],"capInsets":[0,0,0,0]}],[0],0,[0],[0],[0]],[[{"name":"Shark_dead_0085","rect":[1,1181,137,264],"offset":[-8,0],"originalSize":[157,272],"rotated":1,"capInsets":[0,0,0,0]}],[0],0,[0],[0],[0]],[[{"name":"Shark_dead_0109","rect":[831,1057,151,262],"offset":[-2,-2],"originalSize":[157,272],"capInsets":[0,0,0,0]}],[0],0,[0],[0],[0]],[[{"name":"Shark_dead_0105","rect":[839,799,153,256],"offset":[-1,-5],"originalSize":[157,272],"capInsets":[0,0,0,0]}],[0],0,[0],[0],[0]],[[{"name":"Shark_dead_0121","rect":[146,1597,137,264],"offset":[-8,-1],"originalSize":[157,272],"capInsets":[0,0,0,0]}],[0],0,[0],[0],[0]],[[{"name":"Shark_dead_0097","rect":[739,1474,145,252],"offset":[-6,-6],"originalSize":[157,272],"rotated":1,"capInsets":[0,0,0,0]}],[0],0,[0],[0],[0]],[[{"name":"Shark_dead_0077","rect":[418,1597,147,262],"offset":[-3,-2],"originalSize":[157,272],"capInsets":[0,0,0,0]}],[0],0,[0],[0],[0]],[[{"name":"Shark_dead_0089","rect":[567,1597,133,260],"offset":[-11,-2],"originalSize":[157,272],"capInsets":[0,0,0,0]}],[0],0,[0],[0],[0]],[[{"name":"Shark_dead_0081","rect":[1,1597,143,264],"offset":[-4,0],"originalSize":[157,272],"capInsets":[0,0,0,0]}],[0],0,[0],[0],[0]],[[{"name":"Shark_dead_0073","rect":[849,535,147,262],"offset":[-3,-2],"originalSize":[157,272],"capInsets":[0,0,0,0]}],[0],0,[0],[0],[0]],[[{"name":"Shark_dead_0065","rect":[285,1597,131,264],"offset":[-10,-1],"originalSize":[157,272],"capInsets":[0,0,0,0]}],[0],0,[0],[0],[0]],[[{"name":"Shark_dead_0101","rect":[739,1321,151,252],"offset":[-2,-6],"originalSize":[157,272],"rotated":1,"capInsets":[0,0,0,0]}],[0],0,[0],[0],[0]],[[{"name":"Shark_dead_0093","rect":[267,1181,137,254],"offset":[-10,-5],"originalSize":[157,272],"rotated":1,"capInsets":[0,0,0,0]}],[0],0,[0],[0],[0]],[[{"name":"Shark_dead_0113","rect":[702,1621,145,268],"offset":[-4,1],"originalSize":[157,272],"rotated":1,"capInsets":[0,0,0,0]}],[0],0,[0],[0],[0]],[[{"name":"Shark_dead_0069","rect":[857,271,141,262],"offset":[-6,-2],"originalSize":[157,272],"capInsets":[0,0,0,0]}],[0],0,[0],[0],[0]],[[{"name":"Shark_dead_0061","rect":[523,1179,127,266],"offset":[-14,0],"originalSize":[157,272],"rotated":1,"capInsets":[0,0,0,0]}],[0],0,[0],[0],[0]]]]