[1,["ecpdLyjvZBwrvm+cedCcQy","c53u8xzJFNDrlYcoHg8RfO","f0BIwQ8D5Ml7nTNQbh1YlS","9137T2NoxHaZfdqLT5l+Vh","78OuVZVyxFZ5EtZTv1RC6b","06N6UIXKdDqqoxwjnrgfJa","a69VVeNiVIIonJk5X6X/Ft","d0OlI+kf9IBat07j32kUW2","80lc9DwHFExbtkIDb9BzhA","29FYIk+N1GYaeWH/q1NxQO","04iR1oJAtCX5Br93PRjv73","bcWJUaE7VB04Bu3cbQZOfB","c9GckrpvpFeJOEOvz1zxSM","55L3CprHRAa4WIFS9k/v4F","cbUqmw+LFMgKLvMs7dpZh/","34mkIlF2BFzKvVxkGXnCIP","68J8oyAQdFUrqy37MXmbtE","9cZVU8N5pMwIA/zhBzxJCc","01kRjrD+5E94kc3g+NP4f6","90AErWL21A4ZPvtxQ3XG8G","d2kHe6FidKcpV5e1aiNTQM","73oJA92A5OPKpn+ZlUPAj1","f5YSplkaFGTZyjkvPFIvSQ"],["node","_spriteFrame","_N$file","_textureSetter","m_BtnOK","_parent","_N$normalSprite","_N$hoverSprite","_N$disabledSprite","root","LOGOSprite","editPassword","m_ToggleRememberMe","m_LBPromptUser_PW","m_EBUser_PW","m_LBPromptUser_ID","m_EBUser_ID","_N$target","scene","m_BtnClose","m_LBErrorPwAgain","m_LBErrorNewPw","m_LBPromptPwAgain","m_LBPromptNewPw","m_LBPromptOldPw","m_EBnewPwAgain","m_EBNewPw","m_EBoldPw"],[["cc.Node",["_name","_active","_id","_opacity","_parent","_components","_contentSize","_trs","_prefab","_anchorPoint","_children","_color"],-1,1,2,5,7,4,5,2,5],["cc.Label",["_fontSize","_N$verticalAlign","_N$overflow","_string","_enableWrapText","_N$horizontalAlign","_isSystemFontUsed","_enabled","_lineHeight","node","_materials","_N$file"],-6,1,3,6],["cc.Sprite",["_sizeMode","_isTrimmedMode","_type","node","_materials","_spriteFrame"],0,1,3,6],["cc.Node",["_name","_id","_opacity","_active","_components","_trs","_parent","_contentSize","_children","_prefab","_color"],-1,9,7,1,5,2,4,5],"cc.SpriteFrame",["cc.Widget",["_alignFlags","_top","_bottom","_originalWidth","_originalHeight","_left","_right","alignMode","_enabled","node"],-6,1],["cc.Button",["_N$transition","_N$interactable","node","_N$target","clickEvents","_N$pressedColor","_N$hoverColor","_N$disabledColor","_N$normalColor"],1,1,1,9,5,5,5,5],["cc.Node",["_name","_parent","_children","_components","_contentSize","_trs","_color","_anchorPoint"],2,1,2,12,5,7,5,5],["cc.EditBox",["returnType","_N$inputFlag","node","editingDidBegan","textChanged","editingDidEnded","editingReturn","_N$textLabel","_N$placeholderLabel","_N$background"],1,1,9,9,9,9,1,1,1],["cc.SceneAsset",["_name","asyncLoadAssets"],1],["cc.PrefabInfo",["fileId","root"],2,1],["2c412EEZptOU7OgHAzhs0Am",["node","m_EBUser_ID","m_LBPromptUser_ID","m_EBUser_PW","m_LBPromptUser_PW","m_ToggleRememberMe","m_BtnOK","editPassword","LOGOSprite"],3,1,1,1,1,1,1,1,1,1],["cc.Scene",["_name","autoReleaseAssets","_children","_anchorPoint","_trs"],1,2,5,7],["cc.Canvas",["_fitWidth","node","_designResolution"],2,1,5],["cc.Camera",["_clearFlags","_depth","node"],1,1],["cc.ClickEvent",["_componentId","handler","target"],1,1],["cc.Toggle",["_N$transition","_N$isChecked","node","_N$normalColor","_N$target","checkMark","checkEvents"],1,1,5,1,1,9],["8d92aBCcn5BAqYwC85YmsgD",["node","root"],3,1,1]],[[10,0,1,2],[15,0,1,2,3],[3,0,6,4,7,5,2],[2,2,0,3,4,5,3],[1,0,2,9,10,3],[0,0,4,10,5,8,6,7,2],[3,0,6,4,9,10,7,5,2],[3,0,6,4,9,7,5,2],[2,0,3,4,5,2],[8,0,1,2,3,4,5,6,7,8,9,3],[0,0,4,5,11,6,9,7,2],[0,0,1,4,5,6,7,3],[0,0,1,4,5,8,11,6,9,7,3],[0,0,1,4,5,8,6,9,7,3],[0,0,4,5,8,11,6,9,7,2],[2,3,4,5,1],[2,2,3,4,2],[1,3,0,6,1,9,10,11,5],[0,0,4,5,8,6,7,2],[0,0,4,5,8,11,6,7,2],[7,0,1,2,3,4,5,2],[2,2,3,2],[6,1,0,2,4,5,6,7,3,3],[1,0,1,2,9,10,4],[1,7,0,4,6,1,2,9,7],[1,0,2,9,3],[1,7,3,0,6,5,1,9,10,7],[9,0,1,3],[0,0,2,10,5,8,3],[0,0,1,4,10,8,3],[0,0,4,10,5,6,7,2],[0,0,2,4,10,6,7,3],[0,0,4,5,6,7,2],[0,0,1,3,4,5,11,6,9,7,4],[0,0,1,4,5,6,9,7,3],[0,0,4,5,6,9,7,2],[0,0,4,5,8,6,2],[3,0,1,8,4,5,3],[3,0,6,8,4,5,2],[3,0,1,6,8,4,7,5,3],[3,0,2,6,4,9,10,7,5,3],[3,0,6,4,5,2],[3,0,3,6,4,7,5,3],[7,0,1,2,3,6,4,7,5,2],[11,0,1,2,3,4,5,6,7,8,1],[5,0,1,2,9,4],[5,8,7,0,1,2,3,4,9,8],[5,0,5,6,1,2,3,4,9,8],[5,7,0,5,6,1,2,3,4,9,9],[5,0,9,2],[5,0,5,9,3],[5,0,6,9,3],[2,0,1,3,4,5,3],[2,0,1,3,4,3],[2,0,1,3,5,3],[2,0,1,3,3],[2,2,0,1,3,4,5,4],[12,0,1,2,3,4,3],[13,0,1,2,2],[6,2,8,3,1],[6,0,2,4,5,6,7,3,2],[14,0,1,2,3],[1,3,0,4,1,2,9,10,6],[1,3,0,4,5,1,2,9,10,7],[1,3,0,5,1,9,10,5],[1,3,0,8,4,6,5,1,2,9,10,11,9],[1,7,0,4,6,5,1,2,9,8],[16,0,1,2,3,4,5,6,3],[8,0,2,3,4,5,6,7,8,9,2],[17,0,1,1]],[[[{"name":"LobbyBg","rect":[0,0,642,722],"offset":[0,0],"originalSize":[642,722],"capInsets":[0,0,0,0]}],[4],0,[0],[3],[11]],[[{"name":"Mob_SignIn_w_Password","rect":[1,1,218,42],"offset":[0,0],"originalSize":[220,42],"capInsets":[0,0,0,0]}],[4],0,[0],[3],[4]],[[{"name":"Mob_But_w_OK_nor","rect":[90,580,81,42],"offset":[2,-1],"originalSize":[337,104],"capInsets":[0,0,0,0]}],[4],0,[0],[3],[12]],[[[27,"Login",null],[28,"EditPasswordMgr","b5vCyxnCtBOoQgsVY/wBQO",[-3],[-2],[0,"28S0KnpDFAGbfQ32FRawQD",-1]],[29,"root",false,1,[-4,-5,-6,-7,-8,-9,-10,-11,-12,-13,-14,-15,-16,-17,-18,-19,-20,-21,-22],[0,"22zsBaHONLr6iq+EhoXOqN",1]],[37,"SignIn","8bpIUGDGlPx4sDjppBU2s7",[-32,-33],[[44,-31,-30,-29,-28,-27,-26,-25,-24,-23]],[640,360,0,0,0,0,1,1,1,1]],[38,"UserInfo",3,[-35,-36,-37,-38,-39,-40,-41,-42,-43,-44],[[45,45,-10,10,-34]],[0,10,0,0,0,0,1,1,1,1]],[43,"Btn_OK",4,[-48],[[-45,[52,2,false,-46,[8],9],[46,false,0,45,5,5,100,40,-47]],1,4,4],[4,4293059298],[5,337,104],[0,0.5834767135044401,0.3486984567732021],[296,-220,0,0,0,0,1,0.8,0.8,1]],[20,"user_id",4,[-51,-52,-53],[[-49,[47,45,-172.5,-112.5,118,-158,285,40,-50]],1,4],[5,285,40],[-30,-138,0,0,0,0,1,1,1,1]],[20,"user_pw",4,[-56,-57,-58],[[-54,[48,2,45,-172.5,-112.5,183,-223,285,40,-55]],1,4],[5,285,40],[-30,-203,0,0,0,0,1,1,1,1]],[57,"New Node",true,[-59,-60,3,1],[0,0,0],[0,0,0,0,0,0,1,1,1,1]],[30,"toggle",4,[-62,-63,-64],[-61],[5,282.2,58.1],[290,-127,0,0,0,0,1,1,1,1]],[5,"OldPw_EditBox",2,[-66,-67,-68],[-65],[0,"61SLkLIOtBRLiqaN7G4vf/",1],[5,243,40],[795,420,0,0,0,0,1,1,1,1]],[5,"NewPw_EditBox",2,[-70,-71,-72],[-69],[0,"29LoCj6qZPsqKtsJbERCbC",1],[5,243,40],[795,358,0,0,0,0,1,1,1,1]],[5,"NewPwAg_EditBox",2,[-74,-75,-76],[-73],[0,"c1m4fq1hxFVqUvb2R5qsDq",1],[5,243,40],[795,295,0,0,0,0,1,1,1,1]],[39,"Canvas","be5fymlaVFAptd7ZdyTzoP",8,[-79],[[58,true,-77,[5,1280,720]],[49,45,-78]],[5,1280,720],[640,360,0,0,0,0,1,1,1,1]],[31,"Bg","c2kAaC2u1CaJ2vQjaW2HSi",8,[-80,-81,-82],[5,1280,720],[640,360,0,0,0,0,1,1,1,1]],[40,"bg_dark",146,2,[[8,0,-83,[27],28],[59,-85,[4,4292269782],-84]],[0,"ccaRHJVHJHyYmTCN6XsNC5",1],[4,4278190080],[5,1280,720],[640,360,0,0,0,0,1,1,1,1]],[2,"LeftBg",14,[[8,2,-86,[0],1],[50,8,-1,-87]],[5,642,722],[-320,0,0,0,0,0,1,1,1,1]],[2,"RightBg",14,[[8,2,-88,[2],3],[51,32,-1,-89]],[5,642,722],[320,0,0,0,0,0,1,-1,1,1]],[2,"Background",9,[[8,0,-90,[20],21]],[5,23,23],[-113.3,-4.8,0,0,0,0,1,1,1,0]],[5,"Btn_OK",2,[-92],[-91],[0,"f0Ol3nE/dPgacaG0n+GtBj",1],[5,350,100],[644,211,0,0,0,0,1,1,1,1]],[6,"Sprite",19,[[8,0,-93,[31],32]],[0,"87XtORyQxFKbAjcID5GWnp",1],[4,4286085240],[5,303.3,84.24],[-4,10,0,0,0,0,1,1,1,1]],[5,"Btn_Exit",2,[-95],[-94],[0,"0e600PDKBCAJMM84B7P6og",1],[5,155,119],[984,541,0,0,0,0,1,1,1,1]],[7,"Sprite",21,[[15,-96,[33],34]],[0,"02/d0FHM5KNqdkF1CIGAsy",1],[5,58,58],[-47,-33,0,0,0,0,1,1,1,1]],[41,"Main Camera",13,[[61,7,-1,-97]],[0,0,534.6489020144837,0,0,0,1,1,1,1]],[32,"Logo",14,[-98],[5,673,473],[0,125,0,0,0,0,1,0.8,0.8,1]],[53,2,false,24,[4]],[2,"Board_BG",3,[[3,1,0,-99,[5],6]],[5,892,202],[0,-162,0,0,0,0,1,1,1,1]],[42,"New Sprite(Splash)",false,5,[[54,2,false,-100,7]],[5,337,104],[-15,10,0,0,0,0,1,1,1,1]],[22,false,1,5,[[1,"2c412EEZptOU7OgHAzhs0Am","OnClickLogin",3]],[4,4290032820],[4,4293059298],[4,4293059298],5],[2,"user_id_Label",4,[[15,-101,[10],11]],[5,206,42],[-308,-140,0,0,0,0,1,1,1,1]],[2,"user_pw_Label",4,[[15,-102,[12],13]],[5,218,42],[-302,-205,0,0,0,0,1,1,1,1]],[2,"user_id_BACKGROUND_SPRITE",4,[[3,1,0,-103,[14],15]],[5,285,40],[-30,-138,0,0,0,0,1,1,1,1]],[2,"user_pw_BACKGROUND_SPRITE",4,[[3,1,0,-104,[16],17]],[5,285,40],[-30,-203,0,0,0,0,1,1,1,1]],[33,"user_id_PLACEHOLDER_LABEL",false,139,4,[-105],[4,4290493371],[5,283,40],[0,0,1],[-120,-118,0,0,0,0,1,1,1,1]],[62,"Enter text here...",19.9,false,1,1,33,[18]],[10,"user_pw_PLACEHOLDER_LABEL",4,[-106],[4,4292730333],[5,283,40],[0,0,1],[-174.9,-187.1,0,0,0,0,1,1,1,1]],[63,"Default  is Your Pin",22,false,1,1,1,35,[19]],[11,"checkmark",false,9,[-107],[5,23,23],[-113.3,-4.8,0,0,0,0,1,1,1,1]],[55,0,false,37],[2,"New Label",9,[[64,"Remember me",22,1,1,-108,[22]]],[5,145.48,50.4],[-17.3,-5.8,0,0,0,0,1,1,1,1]],[67,3,false,9,[4,4292269782],18,38,[[1,"2c412EEZptOU7OgHAzhs0Am","OnRememberMeToggle",3]]],[34,"TEXT_LABEL",false,6,[-109],[5,283,40],[0,0,1],[-140.5,20,0,0,0,0,1,1,1,1]],[23,25,1,1,41,[23]],[11,"BACKGROUND_SPRITE",false,6,[-110],[5,285,40],[0,-1,0,0,0,0,1,1,1,1]],[21,1,43],[10,"PLACEHOLDER_LABEL",6,[-111],[4,4290493371],[5,283,40],[0,0,1],[-140.5,20,0,0,0,0,1,1,1,1]],[4,0,1,45,[24]],[68,5,6,[[1,"2c412EEZptOU7OgHAzhs0Am","OnUserIDDidBegan",3]],[[1,"2c412EEZptOU7OgHAzhs0Am","OnUserIDTextChanged",3]],[[1,"2c412EEZptOU7OgHAzhs0Am","OnUserIDDidEnd",3]],[[1,"2c412EEZptOU7OgHAzhs0Am","OnUserIDReturn",3]],42,46,44],[35,"TEXT_LABEL",7,[-112],[5,283,40],[0,0,1],[-140.5,20,0,0,0,0,1,1,1,1]],[23,25,1,1,48,[25]],[11,"BACKGROUND_SPRITE",false,7,[-113],[5,285,40],[0,-1,0,0,0,0,1,1,1,1]],[21,1,50],[10,"PLACEHOLDER_LABEL",7,[-114],[4,4290493371],[5,283,40],[0,0,1],[-140.5,20,0,0,0,0,1,1,1,1]],[4,0,1,52,[26]],[9,4,0,7,[[1,"2c412EEZptOU7OgHAzhs0Am","OnUserPWDidBegan",3]],[[1,"2c412EEZptOU7OgHAzhs0Am","OnUserPWTextChanged",3]],[[1,"2c412EEZptOU7OgHAzhs0Am","OnUserPWDidEnd",3]],[[1,"2c412EEZptOU7OgHAzhs0Am","OnUserPWRetrun",3]],49,53,51],[69,1,2],[7,"Bg_Board",2,[[56,1,0,false,-115,[29],30]],[0,"960i7RChxG05fzChrqrnaP",1],[5,700,400],[640,360,0,0,0,0,1,1,1,1]],[22,false,1,19,[[1,"8d92aBCcn5BAqYwC85YmsgD","OnClickOK",1]],[4,4291348680],[4,4293651436],[4,4286085240],20],[60,1,21,[[1,"8d92aBCcn5BAqYwC85YmsgD","OnClickClose",1]],[4,4291348680],[4,4293651436],[4,3363338360],22],[7,"old_pw_BACKGROUND_SPRITE",2,[[3,1,0,-116,[35],36]],[0,"7bEeeFOp1Ns55RQXit5lY9",1],[5,280,45],[794,430,0,0,0,0,1,1,1,1]],[7,"new_pw BACKGROUND_SPRITE",2,[[3,1,0,-117,[37],38]],[0,"28AGZg6pNA5YjQ/EmKhn7j",1],[5,280,45],[794,368,0,0,0,0,1,1,1,1]],[7,"new_pw_ag_BACKGROUND_SPRITE",2,[[3,1,0,-118,[39],40]],[0,"90+giD07pO0pxIvmG6ckC/",1],[5,280,45],[794,305,0,0,0,0,1,1,1,1]],[6,"Title",2,[[65,"Change Password",50,80,false,false,1,1,3,-119,[41],42]],[0,"cbnlFb0z5KUJ+RTOtKSrIo",1],[4,4287758335],[5,475,100.8],[640,510,0,0,0,0,1,1,1,1]],[12,"PLACEHOLDER_LABEL",false,2,[-120],[0,"78fVXOwq5MYLhUnLC566uk",1],[4,4290493371],[5,158,40],[0,0,1],[715,450,0,0,0,0,1,1,1,1]],[66,false,20,false,false,1,1,1,63],[12,"PLACEHOLDER_LABEL",false,2,[-121],[0,"76izj5G1VBhZZ2NBmR32y9",1],[4,4290493371],[5,158,40],[0,0,1],[715,388,0,0,0,0,1,1,1,1]],[24,false,20,false,false,1,1,65],[12,"PLACEHOLDER_LABEL",false,2,[-122],[0,"ceLiwLRelOjoPJua0YJmhT",1],[4,4290493371],[5,158,40],[0,0,1],[715,325,0,0,0,0,1,1,1,1]],[24,false,20,false,false,1,1,67],[6,"Label_OldPw",2,[[17,"Old Password :",25,false,1,-123,[43],44]],[0,"c011AtUzBCRqnV8kPpduyT",1],[4,4294309283],[5,186.28,50.4],[420,430,0,0,0,0,1,1,1,1]],[6,"Label_NewPw",2,[[17,"New Password :",25,false,1,-124,[45],46]],[0,"bf3S55sy5K369fuqe+RlPZ",1],[4,4294309283],[5,202.08,50.4],[428,368,0,0,0,0,1,1,1,1]],[6,"Label_NewPwAg",2,[[17,"New Password Again :",25,false,1,-125,[47],48]],[0,"35Lpz7aHFK/bjDeJAB+SQl",1],[4,4294309283],[5,279.06,50.4],[467,305,0,0,0,0,1,1,1,1]],[36,"BACKGROUND_SPRITE",10,[-126],[0,"01pktjUGlPCoUNIoTAq0JZ",1],[5,243,40]],[16,1,72,[49]],[13,"TEXT_LABEL",false,10,[-127],[0,"8cbMI5WPdMnYSjqMWy6fmU",1],[5,241,40],[0,0,1],[-119.5,20,0,0,0,0,1,1,1,1]],[4,20,1,74,[50]],[14,"PLACEHOLDER_LABEL",10,[-128],[0,"12PJypD+pEQZMyC/fYcZMR",1],[4,4290493371],[5,241,40],[0,0,1],[-119.5,20,0,0,0,0,1,1,1,1]],[4,0,1,76,[51]],[9,5,0,10,[[1,"8d92aBCcn5BAqYwC85YmsgD","OnOldPwDidBegan",1]],[[1,"8d92aBCcn5BAqYwC85YmsgD","OnOldPwTextChanged",1]],[[1,"8d92aBCcn5BAqYwC85YmsgD","OnOldPwDidEnd",1]],[[1,"8d92aBCcn5BAqYwC85YmsgD","OnOldPwReturn",1]],75,77,73],[18,"BACKGROUND_SPRITE",11,[-129],[0,"e8ZzQVXTxEHIo4VTMovebz",1],[5,243,40],[0,10,0,0,0,0,1,1,1,1]],[16,1,79,[52]],[13,"TEXT_LABEL",false,11,[-130],[0,"a9C+FvB0dAcL7teE/GswOZ",1],[5,241,40],[0,0,1],[-119.5,20,0,0,0,0,1,1,1,1]],[25,20,1,81],[14,"PLACEHOLDER_LABEL",11,[-131],[0,"30mQLm/MxIc7S4pZ5MTONb",1],[4,4290493371],[5,241,40],[0,0,1],[-119.5,30,0,0,0,0,1,1,1,1]],[4,0,1,83,[53]],[9,5,0,11,[[1,"8d92aBCcn5BAqYwC85YmsgD","OnNewPwDidBegan",1]],[[1,"8d92aBCcn5BAqYwC85YmsgD","OnNewPwTextChanged",1]],[[1,"8d92aBCcn5BAqYwC85YmsgD","OnNewPwDidEnd",1]],[[1,"8d92aBCcn5BAqYwC85YmsgD","OnNewPwReturn",1]],82,84,80],[19,"prompt",2,[-132],[0,"c7S3GsrFtDrbkmzcnqMJld",1],[4,4278190335],[5,288.06,50.4],[783.7,334.2,0,0,0,0,1,1,1,1]],[26,false,"4~20 characters including A~Z, a~z and 0~9",13,false,1,1,86,[54]],[18,"BACKGROUND_SPRITE",12,[-133],[0,"35pSTLWnVKUbBVoaAemAi1",1],[5,243,40],[0,10,0,0,0,0,1,1,1,1]],[16,1,88,[55]],[13,"TEXT_LABEL",false,12,[-134],[0,"78Pqy0QqZN9ZStJ+a3/UfB",1],[5,241,40],[0,0,1],[-119.5,20,0,0,0,0,1,1,1,1]],[25,20,1,90],[14,"PLACEHOLDER_LABEL",12,[-135],[0,"e7V1u+3yVCGruxdqWeQlKH",1],[4,4290493371],[5,241,40],[0,0,1],[-119.5,30,0,0,0,0,1,1,1,1]],[4,0,1,92,[56]],[9,4,0,12,[[1,"8d92aBCcn5BAqYwC85YmsgD","OnNewPwAgainDidBegan",1]],[[1,"8d92aBCcn5BAqYwC85YmsgD","OnNewPwAgainTextChanged",1]],[[1,"8d92aBCcn5BAqYwC85YmsgD","OnNewPwAgaingDidEnd",1]],[[1,"8d92aBCcn5BAqYwC85YmsgD","OnNewPwAgainRetrun",1]],91,93,89],[19,"prompt",2,[-136],[0,"74KER9rq5K4K7Qce159w1M",1],[4,4278190335],[5,288.06,50.4],[783.7,269.4,0,0,0,0,1,1,1,1]],[26,false,"4~20 characters including A~Z, a~z and 0~9",13,false,1,1,95,[57]]],0,[0,9,1,0,-1,55,0,-1,2,0,-1,15,0,-2,56,0,-3,19,0,-4,21,0,-5,59,0,-6,60,0,-7,61,0,-8,62,0,-9,63,0,-10,65,0,-11,67,0,-12,69,0,-13,70,0,-14,71,0,-15,10,0,-16,11,0,-17,86,0,-18,12,0,-19,95,0,10,25,0,11,55,0,4,28,0,12,40,0,13,36,0,14,54,0,15,34,0,16,47,0,0,3,0,-1,26,0,-2,4,0,0,4,0,-1,5,0,-2,29,0,-3,30,0,-4,31,0,-5,32,0,-6,33,0,-7,35,0,-8,9,0,-9,6,0,-10,7,0,-1,28,0,0,5,0,0,5,0,-1,27,0,-1,47,0,0,6,0,-1,41,0,-2,43,0,-3,45,0,-1,54,0,0,7,0,-1,48,0,-2,50,0,-3,52,0,-1,13,0,-2,14,0,-1,40,0,-1,18,0,-2,37,0,-3,39,0,-1,78,0,-1,72,0,-2,74,0,-3,76,0,-1,85,0,-1,79,0,-2,81,0,-3,83,0,-1,94,0,-1,88,0,-2,90,0,-3,92,0,0,13,0,0,13,0,-1,23,0,-1,16,0,-2,17,0,-3,24,0,0,15,0,17,15,0,0,15,0,0,16,0,0,16,0,0,17,0,0,17,0,0,18,0,-1,57,0,-1,20,0,0,20,0,-1,58,0,-1,22,0,0,22,0,0,23,0,-1,25,0,0,26,0,0,27,0,0,29,0,0,30,0,0,31,0,0,32,0,-1,34,0,-1,36,0,-1,38,0,0,39,0,-1,42,0,-1,44,0,-1,46,0,-1,49,0,-1,51,0,-1,53,0,0,56,0,0,59,0,0,60,0,0,61,0,0,62,0,-1,64,0,-1,66,0,-1,68,0,0,69,0,0,70,0,0,71,0,-1,73,0,-1,75,0,-1,77,0,-1,80,0,-1,82,0,-1,84,0,-1,87,0,-1,89,0,-1,91,0,-1,93,0,-1,96,0,18,8,1,5,8,3,5,8,55,19,58,55,4,57,55,20,96,55,21,87,55,22,68,55,23,66,55,24,64,55,25,94,55,26,85,55,27,78,136],[0,0,0,0,0,0,0,0,0,0,0,0,0,0,0,0,0,0,0,0,0,0,0,0,0,0,0,0,0,0,0,0,0,0,0,0,0,0,0,0,0,0,0,0,0,0,0,0,0,0,0,0,0,0,0,0,0,0,38,57,57,57,58,58,58,64,66,68,87,96],[-1,1,-1,1,-1,-1,1,1,-1,1,-1,1,-1,1,-1,1,-1,1,-1,-1,-1,1,-1,-1,-1,-1,-1,-1,1,-1,1,-1,1,-1,1,-1,1,-1,1,-1,1,-1,2,-1,2,-1,2,-1,2,-1,-1,-1,-1,-1,-1,-1,-1,-1,1,6,7,8,6,7,8,2,2,2,2,2],[0,5,0,5,0,0,6,13,0,7,0,14,0,15,0,8,0,8,0,0,0,16,0,0,0,0,0,0,17,0,6,0,7,0,18,0,3,0,3,0,3,0,1,0,1,0,1,0,1,0,0,0,0,0,0,0,0,0,19,2,2,9,2,2,9,1,1,1,10,10]],[[{"name":"default_toggle_normal","rect":[0,0,28,28],"offset":[0,0],"originalSize":[28,28],"capInsets":[0,0,0,0]}],[4],0,[0],[3],[20]],[[{"name":"Mob_SignIn_Field","rect":[395,1,51,43],"offset":[0,0],"originalSize":[51,43],"capInsets":[6,6,7,6]}],[4],0,[0],[3],[4]],[[{"name":"default_toggle_checkmark","rect":[4,5,20,18],"offset":[0,0],"originalSize":[28,28],"capInsets":[0,0,0,0]}],[4],0,[0],[3],[21]],[[{"name":"Mob_SignIn_w_MobileID","rect":[17,0,206,42],"offset":[0,0],"originalSize":[240,42],"capInsets":[0,0,0,0]}],[4],0,[0],[3],[22]]]]