[1,0,0,[["cc.JsonAsset",["_name","json"],1]],[[0,0,1,3]],[[0,"steer_debug",{"STEER":{"DRAW_LINE":false,"DRAW_POINT":false,"FIXED_TIMESTEP":0.1,"ANGLE":0,"X_RANGE":[-5,5],"Y_RANGE":[-3,3],"SHARK":{"MAX_SPEED":120,"MAX_STEER":1,"MIN_RANGE":5,"ANGLE":0,"PATH":[[[-4,-4],[-2,-1],[4,6]],[[-4,-4],[2,0],[5,6]],[[-4,-5],[2,0],[6,6]],[[-6,-2],[1,0],[7,3]],[[-3,5],[1,1],[7,-3]],[[-7,5],[-1,-1],[4,-5]],[[-1,5],[0,0],[1,-5]],[[-1,-5],[0,0],[1,5]]]},"ANGLER_FISH":{"MAX_SPEED":100,"MAX_STEER":1,"MIN_RANGE":3,"ANGLE":0,"PATH":[[[-4,-4],[-2,-1],[3,4]],[[-4,-4],[2,0],[4,4]],[[4,-5],[0,0],[-4,5]],[[6,-4],[1,0],[-2,5]],[[6,5],[1,0],[-2,-5]],[[-6,5],[-1,0],[2,-5]],[[-6,1],[0,0],[6,1]],[[6,1],[0,0],[-6,1]]]},"MANTARAY":{"MAX_SPEED":80,"MAX_STEER":1,"MIN_RANGE":3,"ANGLE":0,"PATH":[[[-4,-4],[-2,-1],[3,4]],[[-4,-4],[2,0],[4,4]],[[7,-3],[1,0],[-7,1]],[[-7,5],[0,0],[7,-2]],[[6,5],[1,0],[-2,-5]],[[-6,5],[-1,0],[2,-5]],[[-6,1],[0,0],[6,1]],[[6,1],[0,0],[-6,1]]]},"GIANT_BUTTERFLY":{"MAX_SPEED":140,"MAX_STEER":1,"MIN_RANGE":3,"ANGLE":0,"PATH":[[[-6,-5],[-2,-1],[4,5]],[[-6,-5],[2,0],[5,5]],[[-5,-6],[0,0],[6,6]],[[-6,-5],[-1,0],[7,3]],[[-7,5],[-2,0],[2,-5]],[[-2,5],[2,0],[7,-5]],[[-7,-1],[0,0],[7,1]],[[7,-1],[0,0],[-7,1]],[[-1,5],[0,0],[1,-5]],[[-1,-5],[0,0],[1,5]]]},"GIANT_PUFFER_FISH":{"MAX_SPEED":150,"MAX_STEER":1,"MIN_RANGE":3,"ANGLE":0,"PATH":[[[-6,-5],[-2,-1],[4,5]],[[-6,-5],[2,0],[5,5]],[[-5,-6],[0,0],[6,6]],[[-6,-5],[-1,0],[7,3]],[[-7,5],[-2,0],[2,-5]],[[-2,5],[2,0],[7,-5]],[[-7,-1],[0,0],[7,1]],[[7,-1],[0,0],[-7,1]],[[-1,5],[0,0],[1,-5]],[[-1,-5],[0,0],[1,5]]]},"GIANT_NEMO":{"MAX_SPEED":130,"MAX_STEER":1,"MIN_RANGE":3,"ANGLE":0,"PATH":[[[-6,-5],[-2,-1],[4,5]],[[-6,-5],[2,0],[5,5]],[[-5,-6],[0,0],[6,6]],[[-6,-5],[-1,0],[7,3]],[[-7,5],[-2,0],[2,-5]],[[-2,5],[2,0],[7,-5]],[[-7,-1],[0,0],[7,1]],[[7,-1],[0,0],[-7,1]],[[-1,5],[0,0],[1,-5]],[[-1,-5],[0,0],[1,5]]]},"KILLER_WHALE":{"MAX_SPEED":70,"MAX_STEER":1,"MIN_RANGE":3,"DRAW_POINT":false,"ANGLE":0,"PATH":[[[-8,-6],[-2,-1],[7,6]],[[-8,-6],[2,0],[7,6]],[[-8,-7],[0,0],[8,7]],[[-8,-6],[-1,0],[9,4]],[[-8,6],[-2,0],[3,-7]],[[-3,8],[2,0],[8,-6]],[[-8,-2],[0,0],[8,2]],[[8,-2],[0,0],[-8,2]],[[-2,8],[0,0],[2,-8]],[[-2,-8],[0,0],[2,8]]]},"HUMPBACK_WHALE":{"MAX_SPEED":50,"MAX_STEER":1,"MIN_RANGE":3,"DRAW_POINT":false,"ANGLE":0,"PATH":[[[-9,-7],[-2,-1],[9,8]],[[-9,-9],[2,0],[9,8]],[[-9,-8],[0,0],[9,8]],[[-9,-7],[-1,0],[9,5]],[[-9,7],[-2,0],[3,-9]],[[-4,9],[2,0],[9,-7]],[[-9,-3],[0,0],[9,4]],[[9,-3],[0,0],[-8,4]],[[-3,9],[0,0],[3,-9]],[[-3,-9],[0,0],[3,9]]]},"BUTTERFLY":{"MAX_SPEED":200,"MAX_STEER":10,"MIN_RANGE":10,"ANGLE":0,"FIXED_TIMESTEP":0.03,"DRAW_POINT":false,"ROW":{"INTERVAL":650},"PATH":[[[8,5],[2,-2],[1,-2],[-2,2],[-3,2],[-8,-5]],[[-7,-5],[-3,2],[-2,2],[1,-2],[2,-2],[7,5]],[[7,-5],[2,2],[1,2],[-2,-2],[-3,-2],[-8,5]],[[-7,-5],[-2,2],[-1,2],[2,-2],[3,-2],[7,5]],[[-8,0],[-3,3],[-2,2],[-1,-2],[0,-2],[4,0],[5,-1],[8,-5]],[[8,2],[3,-2],[2,-1],[0,2],[-1,2],[-3,-2],[-4,-2],[-8,2]],[[8,-3],[3,3],[2,3],[0,-1],[-1,0],[-3,2],[-4,2],[-8,0]],[[6,-2],[1,-1],[-1,-1],[-1.5,0],[-1,1],[0,1.5],[1,1],[1.5,0],[1,-1],[0,-1.5],[-1,-1],[-10,-2]],[[2.5,-7],[4.5,0],[4.5,1.5],[2,2.5],[0.5,1.5],[0.5,0],[1,-1],[3,-1],[3,0.5],[2.5,7]],[[-1,-7],[-3,0],[-2,1.5],[-1,1.5],[0,0],[-0.5,-1],[-2,-1.5],[-3,1],[-1,6.5]],[[-2.5,7],[-3,0],[-2,-1.5],[-0.5,-1.5],[0,0],[-0.5,1.5],[-1.5,1.5],[-2.5,1.5],[-3,-1],[-2.5,-7]],[[2.5,7],[3,0],[2,-1.5],[1,-1.5],[0,0],[0.5,1.5],[2.5,1.5],[3,-1],[2.5,-7]],[[-1,-7],[-3,0],[-1,2],[-2,0],[-4,4],[-6,6]],[[2,7],[3,0],[2,2],[1,-1],[2,-2],[5,-4],[5,-7]],[[-6,-6],[-4,-1],[-1,-1],[-1,2],[2,1],[4,3],[5,7]]]},"LOBSTER":{"MAX_SPEED":100,"MAX_STEER":10,"MIN_RANGE":8,"ANGLE":0,"DRAW_POINT":false,"ROW":{"INTERVAL":1000},"PATH":[[[6,1],[5,0],[4.5,-0.75],[4.5,-1],[2.5,-0.5],[1.5,1.25],[0.5,1],[-0.5,1.5],[-1.5,2.25],[-2.5,2],[-4.5,1.5],[-4.25,0.75],[-5,0],[-6,-1]],[[9,4.5],[2,-2],[-2,2],[-9,-3]],[[-9,-4.5],[-4,2],[1,-2],[6,0],[9,-4.5]],[[-6.5,1],[0,-3],[7,1]],[[6.5,-1],[0,3],[-7,-1]],[[6.5,4],[1,3],[-2,-1],[-2,-6.5]],[[-6.5,5],[-3,3],[0,-1],[1,-6.5]],[[-3,-5],[-2,-1],[0,2],[4,6.5]],[[4,-5],[3,-1],[0,2],[-6.5,5]],[[2.5,-5],[4,0],[2,2],[0,0],[2,-2],[4,0.5],[2.5,6.5]],[[-2.5,-5],[-4,0],[-2,2],[0,0],[-2,-2],[-4,0.5],[-2.5,6.5]],[[-2.5,5],[-4,0],[-2,-2],[0,0],[-2,2],[-4,-0.5],[-2.5,-6.5]],[[2.5,5],[4,0],[2,-2],[0,0],[2,2],[4,-0.5],[2.5,-6.5]],[[-4,-5],[-4,0],[-2,2],[0,0],[2,2],[4,-2],[2,-6.5]],[[4,-5],[4,0],[2,2],[0,0],[-2,-1],[-4,0],[-8,6.5]]]},"SINGLE_LOBSTER":{"MAX_SPEED":70,"MAX_STEER":10,"MIN_RANGE":8,"ANGLE":0,"DRAW_POINT":false,"PATH":[[[6,1],[5,0],[4.5,-0.75],[4.5,-1],[2.5,-0.5],[1.5,1.25],[0.5,1],[-0.5,1.5],[-1.5,2.25],[-2.5,2],[-4.5,1.5],[-4.25,0.75],[-5,0],[-6,-1]],[[9,4.5],[2,-2],[-2,2],[-9,-3]],[[-9,-4.5],[-4,2],[1,-2],[6,0],[9,-4.5]],[[-6.5,1],[0,-3],[7,1]],[[6.5,-1],[0,3],[-7,-1]],[[6.5,4],[1,3],[-2,-1],[-2,-6.5]],[[-6.5,5],[-3,3],[0,-1],[1,-6.5]],[[-3,-5],[-2,-1],[0,2],[4,6.5]],[[4,-5],[3,-1],[0,2],[-6.5,5]],[[2.5,-5],[4,0],[2,2],[0,0],[2,-2],[4,0.5],[2.5,6.5]],[[-2.5,-5],[-4,0],[-2,2],[0,0],[-2,-2],[-4,0.5],[-2.5,6.5]],[[-2.5,5],[-4,0],[-2,-2],[0,0],[-2,2],[-4,-0.5],[-2.5,-6.5]],[[2.5,5],[4,0],[2,-2],[0,0],[2,2],[4,-0.5],[2.5,-6.5]],[[-4,-5],[-4,0],[-2,2],[0,0],[2,2],[4,-2],[2,-6.5]],[[4,-5],[4,0],[2,2],[0,0],[-2,-1],[-4,0],[-8,6.5]]]},"GURNARD":{"MAX_SPEED":170,"MAX_STEER":5,"MIN_RANGE":8,"ANGLE":0,"DRAW_POINT":false,"GROUP":{"X_SPACE":70,"Y_SPACE":50,"FORMATION":[[0,0],[-2,-1],[-1,-1],[0,-1],[1,-1],[2,-1],[-2,-2],[-1,-2],[0,-2],[1,-2],[2,-2],[0,-3],[0,-4],[0,-5]]},"PATH":[[[8,3],[0,0],[-8,-3]],[[-8,3],[0,0],[8,-3]],[[7,-5],[0,0],[-7,5]],[[-7,-5],[0,0],[7,5]]]},"SINGLE_GURNARD":{"MAX_SPEED":180,"MAX_STEER":2,"MIN_RANGE":8,"ANGLE":0,"PATH":[[[-5,-7],[-1,-2],[1,0],[2,2],[5,7]],[[5,-7],[2,-2],[-2,0],[-4,2],[-5,7]],[[7,2],[3,0],[0,-1],[-3,-1],[-6,-1]],[[-7,3],[-4,1],[-1,0],[2,0],[6,-1]],[[-2,-7],[1,-2],[3,0],[4,2],[6,7]],[[-6,7],[-4,1],[-1,0],[2,0],[6,-1]],[[-1,7],[0,2],[1,0],[3,-2],[6,-7]],[[6,-7],[4,-2],[3,0],[2,2],[1,7]],[[1,7],[2,2],[3,0],[4,-2],[6,-7]],[[-2,-7],[-3,-2],[-3,0],[-4,2],[-5,7]]]},"SINGLE_NEMO":{"MAX_SPEED":190,"MAX_STEER":10,"MIN_RANGE":8,"ANGLE":0,"PATH":[[[-5,-7],[-1,-2],[1,0],[2,2],[5,7]],[[5,-7],[2,-2],[-2,0],[-4,2],[-5,7]],[[7,2],[3,0],[0,-1],[-3,-1],[-6,-1]],[[-7,3],[-4,1],[-1,0],[2,0],[6,-1]],[[-2,-7],[1,-2],[3,0],[4,2],[6,7]],[[-6,7],[-4,1],[-1,0],[2,0],[6,-1]],[[-1,7],[0,2],[1,0],[3,-2],[6,-7]],[[6,-7],[4,-2],[3,0],[2,2],[1,7]],[[1,7],[2,2],[3,0],[4,-2],[6,-7]],[[-2,-7],[-3,-2],[-3,0],[-4,2],[-5,7]]]},"PUFFER_FISH":{"MAX_SPEED":100,"MAX_STEER":4,"MIN_RANGE":8,"ANGLE":0,"PATH":[[[-4,-4],[-1,-2],[1,0],[2,2],[4,4]],[[4,-4],[2,-2],[-2,0],[-4,2],[-5,4]],[[6,2],[3,0],[0,-1],[-3,-1],[-6,-1]],[[-6,3],[-4,1],[-1,0],[2,0],[6,-1]],[[-2,-4],[1,-2],[3,0],[4,2],[6,4]],[[-6,4],[-4,1],[-1,0],[2,0],[6,-1]],[[-1,4],[0,2],[1,0],[3,-2],[6,-4]],[[6,-5],[4,-2],[3,0],[2,2],[1,5]],[[1,4],[2,2],[3,0],[4,-2],[6,-5]],[[-2,-5],[-3,-2],[-3,0],[-4,2],[-5,5]]]},"SAIL_FISH":{"MAX_SPEED":130,"MAX_STEER":4,"MIN_RANGE":8,"ANGLE":0,"PATH":[[[-5,-5],[-1,-2],[1,0],[2,2],[5,5]],[[4,-4],[2,-2],[-2,0],[-4,2],[-5,4]],[[6,2],[3,0],[0,-1],[-3,-1],[-6,-1]],[[-6,3],[-4,1],[-1,0],[2,0],[7,-1]],[[-2,-4],[1,-2],[3,0],[4,2],[7,4]],[[-6,4],[-4,1],[-1,0],[2,0],[7,-1]],[[-1,4],[0,2],[1,0],[3,-2],[7,-4]],[[6,-5],[4,-2],[3,0],[2,2],[1,5]],[[1,4],[2,2],[3,0],[4,-2],[7,-5]],[[-2,-5],[-3,-2],[-3,0],[-4,2],[-7,5]]]},"SNAIL_FISH":{"MAX_SPEED":80,"MAX_STEER":4,"MIN_RANGE":8,"ANGLE":0,"PATH":[[[-5,-5],[-1,-2],[1,0],[2,2],[5,5]],[[4,-4],[2,-2],[-2,0],[-4,2],[-5,4]],[[6,2],[3,0],[0,-1],[-3,-1],[-6,-1]],[[-6,3],[-4,1],[-1,0],[2,0],[7,-1]],[[-2,-4],[1,-2],[3,0],[4,2],[7,4]],[[-6,4],[-4,1],[-1,0],[2,0],[7,-1]],[[-1,4],[0,2],[1,0],[3,-2],[7,-4]],[[6,-5],[4,-2],[3,0],[2,2],[1,5]],[[1,4],[2,2],[3,0],[4,-2],[7,-5]],[[-2,-5],[-3,-2],[-3,0],[-4,2],[-6,5]]]},"OCTOPUS":{"MAX_SPEED":100,"MAX_STEER":6,"MIN_RANGE":7,"ANGLE":0,"DRAW_POINT":false,"PATH":[[[-6,-6],[-1,-2],[1,0],[0,2],[0,6]],[[6,-6],[2,-2],[-2,0],[-4,2],[-7,6]],[[6,2],[3,0],[0,-1],[-3,-1],[-7,-1]],[[-6,3],[-4,1],[-1,0],[2,0],[7,-1]],[[6,5],[1,0],[-2,-6]],[[-6,5],[-1,0],[2,-6]],[[-6,1],[0,0],[7,1]],[[6,1],[0,0],[-7,1]]]},"SEA_TURTLE":{"MAX_SPEED":130,"MAX_STEER":1,"MIN_RANGE":3,"ANGLE":0,"DRAW_POINT":false,"PATH":[[[-6,-6],[0,0],[1,7]],[[6,-6],[3,-2],[1,1],[-4,-1],[-4.5,-7]],[[-7,-1],[1,-2],[2,7]],[[3,-7],[3,-2],[1,1],[-7,0]],[[6,0],[2,2],[-2,0],[-7,0]],[[0,-7],[-1,0],[1,2],[2,7]],[[-1,-6],[3,-1],[-1,5]],[[6,0],[2,2],[-2,1],[-6,5]]]},"NEMO":{"MAX_SPEED":150,"MAX_STEER":10,"MIN_RANGE":6,"ANGLE":0,"GROUP":{"X_SPACE":85,"Y_SPACE":45,"FORMATION":[[0,-1],[-0.5,-1.5],[0.5,-1.5],[0,-2],[-0.5,-2.5],[0.5,-2.5],[0,-3]]},"PATH":[[[-6.5,-1],[-3,-2],[-0.5,0],[3,1],[6.5,-1]],[[-6.5,-1],[-3,2],[0,0],[3,-3],[6.5,-1]],[[6.5,-1],[3,2],[0,0],[-3,1],[-6.5,-1]],[[6.5,1],[3,-2],[0,0],[-3,1],[-6.5,-1]],[[-4,-6],[-3,-3],[0,0],[3,2],[6.5,0]],[[4,-5],[0,-3],[0,0],[3,2],[6.5,1]],[[-4,6],[-3,3],[0,0],[3,-2.5],[6.5,0]],[[4,6],[-1,4],[-1,-0.5],[3,-2.5],[6.5,0]],[[-4,-6],[0,-3],[0,0],[-3,2],[-6.5,0]],[[4,-5],[2,-3],[0,0],[-3,2],[-6.5,0]],[[-4,6],[2,3],[2,-2],[-3,-3],[-6.5,0]],[[4,6],[1,3],[0,0],[-3,-2.5],[-6.5,-1]],[[6.5,0],[2,0],[0,-1],[-3,1],[-6.5,-1]],[[-6.5,0],[-3,0],[-0.5,0],[3,1],[6.5,-1]]]},"BOMB_CRAB":{"MAX_SPEED":130,"MAX_STEER":10,"MIN_RANGE":3,"ANGLE":0,"DRAW_POINT":false,"PATH":[[[4,5],[1,1],[0.5,0.5],[0,0],[-0.5,-0.5],[0,-1],[0.5,0],[0,0.5],[-2,3],[-3,5]],[[-3,-5],[-0.5,-0.5],[0,-0.5],[0,0],[0,1],[-0.5,0],[0,-0.5],[0,-1],[1,-3],[3,-5]],[[-6.5,0],[0,-1],[0.5,0],[0,0.5],[-0.5,0],[0,-0.5],[1,0],[6.5,1]]]},"FLASH_SHARK":{"MAX_SPEED":130,"MAX_STEER":3,"MIN_RANGE":5,"ANGLE":0,"PATH":[[[-4,-4],[-2,-1],[4,6]],[[-4,-4],[2,0],[5,6]],[[-4,-5],[2,0],[6,6]],[[-6,-2],[1,0],[7,3]],[[-3,5],[1,1],[7,-3]],[[-7,5],[-1,-1],[4,-5]],[[-1,5],[0,0],[1,-5]],[[-1,-5],[0,0],[1,5]]]},"TWISTER_OCTOPUS":{"MAX_SPEED":100,"MAX_STEER":3,"MIN_RANGE":5,"ANGLE":0,"PATH":[[[-4,-4],[-1,-2],[1,0],[2,2],[4,4]],[[4,-4],[2,-2],[-2,0],[-4,2],[-5,4]],[[6,2],[3,0],[0,-1],[-3,-1],[-6,-1]],[[-6,3],[-4,1],[-1,0],[2,0],[6,-1]],[[6,5],[1,0],[-2,-5]],[[-6,5],[-1,0],[2,-5]],[[-6,1],[0,0],[6,1]],[[6,1],[0,0],[-6,1]]]},"LASER_CRAB":{"MAX_SPEED":130,"MAX_STEER":10,"MIN_RANGE":3,"ANGLE":0,"DRAW_POINT":false,"PATH":[[[4,5],[1,1],[0.5,0.5],[0,0],[-0.5,-0.5],[0,-1],[0.5,0],[0,0.5],[-2,3],[-3,5]],[[-3,-5],[-0.5,-0.5],[0,-0.5],[0,0],[0,1],[-0.5,0],[0,-0.5],[0,-1],[1,-3],[3,-5]],[[-6.5,0],[0,-1],[0.5,0],[0,0.5],[-0.5,0],[0,-0.5],[1,0],[6.5,1]]]},"DRILL_CRAB":{"MAX_SPEED":130,"MAX_STEER":10,"MIN_RANGE":3,"ANGLE":0,"DRAW_POINT":false,"PATH":[[[4,5],[1,1],[0.5,0.5],[0,0],[-0.5,-0.5],[0,-1],[0.5,0],[0,0.5],[-2,3],[-3,5]],[[-3,-5],[-0.5,-0.5],[0,-0.5],[0,0],[0,1],[-0.5,0],[0,-0.5],[0,-1],[1,-3],[3,-5]],[[-6.5,0],[0,-1],[0.5,0],[0,0.5],[-0.5,0],[0,-0.5],[1,0],[6.5,1]]]},"KING_SPIDER_CRAB":{"MAX_SPEED":150,"MAX_STEER":15,"MIN_RANGE":10,"ANGLE":0,"DRAW_POINT":false,"REPEAT":20,"PATH":[[[-3,-2],[3,-2],[3,2],[-3,2]],[[3,-2],[-3,-2],[-3,2],[3,2]]]},"MULTI_BOMB_CRAB":{"MAX_SPEED":130,"MAX_STEER":10,"MIN_RANGE":3,"ANGLE":0,"DRAW_POINT":false,"PATH":[[[4,5],[1,1],[0.5,0.5],[0,0],[-0.5,-0.5],[0,-1],[0.5,0],[0,0.5],[-2,3],[-3,5]],[[-3,-5],[-0.5,-0.5],[0,-0.5],[0,0],[0,1],[-0.5,0],[0,-0.5],[0,-1],[1,-3],[3,-5]],[[-6.5,0],[0,-1],[0.5,0],[0,0.5],[-0.5,0],[0,-0.5],[1,0],[6.5,1]]]},"WHEEL_CRAB":{"MAX_SPEED":130,"MAX_STEER":10,"MIN_RANGE":3,"ANGLE":0,"DRAW_POINT":false,"PATH":[[[4,5],[1,1],[0.5,0.5],[0,0],[-0.5,-0.5],[0,-1],[0.5,0],[0,0.5],[-2,3],[-3,5]],[[-3,-5],[-0.5,-0.5],[0,-0.5],[0,0],[0,1],[-0.5,0],[0,-0.5],[0,-1],[1,-3],[3,-5]],[[-6.5,0],[0,-1],[0.5,0],[0,0.5],[-0.5,0],[0,-0.5],[1,0],[6.5,1]]]},"FIRE_STORM":{"MAX_SPEED":130,"MAX_STEER":1,"MIN_RANGE":3,"ANGLE":0,"PATH":[[[-6,-5],[-2,-1],[4,5]],[[-6,-5],[2,0],[5,5]],[[-5,-6],[0,0],[6,6]],[[-6,-5],[-1,0],[7,3]],[[-7,5],[-2,0],[2,-5]],[[-2,5],[2,0],[7,-5]],[[-7,-1],[0,0],[7,1]],[[7,-1],[0,0],[-7,1]],[[-1,5],[0,0],[1,-5]],[[-1,-5],[0,0],[1,5]]]},"KING_ANGLER_FISH":{"MAX_SPEED":120,"PATH":[[[10,5],[0,0],[-10,-5]],[[9,-7],[0,0],[-9,7]],[[10,0],[0,0],[-10,0]]]},"KING_LACOSTE":{"MAX_SPEED":100,"DRAW_POINT":false,"MIN_RANGE":3,"PATH":[[[7,7],[1.5,1.5],[-7,-7]],[[0,8],[-1.5,2.5],[-4,-8]],[[10,6],[2,1],[-10,-6]]]},"FLAT_FISH":{"MAX_SPEED":150,"MAX_STEER":100,"MIN_RANGE":3,"DRAW_POINT":false,"PATH":[[[-7,-1],[-2.5,-1],[0,0],[2.5,1],[7,1]],[[-7,1],[-1.5,2],[0,0],[2.5,-1],[7,-1]],[[-7,2],[-2.5,1],[0,0],[2.5,-2],[2,-7]],[[-6.5,-7],[-1.5,-1.5],[-2,1],[-7,7]],[[-6.5,-7],[-1.5,-1.5],[-2,0],[-5,7]],[[-0.5,-6],[-1.5,-1.5],[-2,1],[-7,7]],[[-0.5,-7],[-1.5,-1.5],[-2,1],[-2,7]],[[-2,-7],[-1,-1],[1,1],[2,7]],[[2,-7],[1,-1],[-1,1],[-2,7]]]},"SAWTOOTH_SHARK":{"MAX_SPEED":130},"CRAB":{"MAX_SPEED":130,"MAX_STEER":3,"MIN_RANGE":4,"ANGLE":0,"DRAW_POINT":false,"PATH":[[[1,7],[0,0],[7,2]],[[-1,7],[0,0],[7,-2]],[[1,7],[0,0],[0,-7]],[[-7,0],[0,0],[7,0]]]},"BUFFALO":{"MAX_SPEED":200},"LUCKY_SHAMROCK":{"MAX_SPEED":100}}}]],0,0,[],[],[]]